ai_dashboard/__init__.py
ai_dashboard/constants.py
ai_dashboard/errors.py
ai_dashboard/json_encoder.py
ai_dashboard/types.py
ai_dashboard/api/__init__.py
ai_dashboard/api/client.py
ai_dashboard/api/endpoints.py
ai_dashboard/api/helpers.py
ai_dashboard/dashboard/__init__.py
ai_dashboard/dashboard/dashboard.py
ai_dashboard/tabs/__init__.py
ai_dashboard/tabs/abstract_tab.py
ai_dashboard/tabs/category_view/__init__.py
ai_dashboard/tabs/category_view/category_view.py
ai_dashboard/tabs/chart_view/__init__.py
ai_dashboard/tabs/chart_view/chart_view.py
ai_dashboard/tabs/data_report/__init__.py
ai_dashboard/tabs/data_report/constants.py
ai_dashboard/tabs/data_report/data_report.py
ai_dashboard/tabs/data_report/markdown.py
ai_dashboard/tabs/data_report/blocks/__init__.py
ai_dashboard/tabs/data_report/blocks/base.py
ai_dashboard/tabs/data_report/blocks/basic.py
ai_dashboard/tabs/data_report/blocks/charts.py
ai_dashboard/tabs/data_report/blocks/connected.py
ai_dashboard/tabs/data_report/blocks/layout.py
ai_dashboard/tabs/data_report/blocks/lists.py
ai_dashboard/tabs/data_report/blocks/marks.py
ai_dashboard/tabs/data_report/blocks/media.py
ai_dashboard/tabs/document_view/__init__.py
ai_dashboard/tabs/document_view/document_view.py
tests/__init__.py
tests/conftest.py
tests/test_script.py
ai_dashboard-0.2.22.dist-info/LICENSE
ai_dashboard-0.2.22.dist-info/METADATA
ai_dashboard-0.2.22.dist-info/WHEEL
ai_dashboard-0.2.22.dist-info/top_level.txt
ai_dashboard-0.2.22.dist-info/RECORD
