Metadata-Version: 2.1
Name: ai-dashboard
Version: 0.2.22
Home-page: https://tryrelevance.com/
Author: Relevance AI
Author-email: dev@tryrelevance.com
License-File: LICENSE
Requires-Dist: requests (>=2.0.0)
Requires-Dist: pandas (>=1.3.5)
Requires-Dist: plotly (>=5.3.1)
Provides-Extra: graphs
Provides-Extra: markdown
Requires-Dist: marko (>=1.2.2) ; extra == 'markdown'
Provides-Extra: tests
Requires-Dist: pytest ; extra == 'tests'
Requires-Dist: pytest-xdist ; extra == 'tests'
Requires-Dist: pytest-cov ; extra == 'tests'
